{
  "id": "mr9vab4xa",
  "slug": "app-1617284064442-argent-mr9vab4xa",
  "name": "Argent",
  "device": "mobile",
  "description": "DeFi at a tap.",
  "icon": "https://res.cloudinary.com/ape-unit/image/upload/v1617277191/w5rcue0keamvq6midljf.png",
  "screens": [
    {
      "id": "aes5wtex4",
      "image": "https://res.cloudinary.com/ape-unit/image/upload/v1617284612/dcttfnmb5nhsfmlgxe0v.png",
      "userflow": "gmc0zdfli",
      "tags": [
        "mywth04j4"
      ]
    },
    {
      "id": "pp5lg7izf",
      "image": "https://res.cloudinary.com/ape-unit/image/upload/v1617284120/uiyhbw9dxoms1v9yto3n.png",
      "userflow": "urnsc8ap3"
    },
    {
      "id": "p92w0nyqk",
      "image": "https://res.cloudinary.com/ape-unit/image/upload/v1617284151/wumtrrif89wrpazxuhbe.png",
      "userflow": "urnsc8ap3",
      "tags": [
        "szojdpfpo"
      ]
    },
    {
      "id": "cncg2zhqu",
      "image": "https://res.cloudinary.com/ape-unit/image/upload/v1617284185/nmhwmktmvqh3p8enytpe.png",
      "userflow": "urnsc8ap3",
      "tags": [
        "szojdpfpo"
      ]
    },
    {
      "id": "nslutbdj9",
      "image": "https://res.cloudinary.com/ape-unit/image/upload/v1617284211/oc3yyxi1jvyaqx6dgyhn.png",
      "userflow": "urnsc8ap3",
      "tags": [
        "szojdpfpo"
      ]
    },
    {
      "id": "p89teo7ud",
      "image": "https://res.cloudinary.com/ape-unit/image/upload/v1617284238/cfqclxkstf2dqxlfuk7t.png",
      "userflow": "urnsc8ap3",
      "tags": [
        "szojdpfpo"
      ]
    },
    {
      "id": "lhqmdkq5h",
      "image": "https://res.cloudinary.com/ape-unit/image/upload/v1617284310/hi0tl08x6hqe2gbjsqbu.png",
      "userflow": "gmc0zdfli",
      "tags": []
    },
    {
      "id": "sh7adnu5k",
      "image": "https://res.cloudinary.com/ape-unit/image/upload/v1617284346/nccwpfuaxl0eamnximog.png",
      "userflow": "gmc0zdfli",
      "tags": [
        "u93yuzxj8"
      ]
    },
    {
      "id": "b3ykevf28",
      "image": "https://res.cloudinary.com/ape-unit/image/upload/v1617284386/nqlxejgzjn5mq79sxhk3.png",
      "userflow": "gmc0zdfli",
      "tags": [
        "u93yuzxj8"
      ]
    },
    {
      "id": "ksqanm03k",
      "image": "https://res.cloudinary.com/ape-unit/image/upload/v1617284414/ffrp6jryx88jhw6hwedn.png",
      "userflow": "gmc0zdfli",
      "tags": [
        "u93yuzxj8"
      ]
    },
    {
      "id": "fhn844pgm",
      "image": "https://res.cloudinary.com/ape-unit/image/upload/v1617284447/swdc5inop7pq2qrlhhjl.png",
      "userflow": "gmc0zdfli",
      "tags": [
        "z7yu0eq11",
        "0nvueu7a8"
      ]
    },
    {
      "id": "wfuwapa3x",
      "image": "https://res.cloudinary.com/ape-unit/image/upload/v1617284490/sh0ow4lbexkjl7bo0tbh.png",
      "userflow": "gmc0zdfli",
      "tags": [
        "0nvueu7a8",
        "z7yu0eq11"
      ]
    },
    {
      "id": "e8wzj3hih",
      "image": "https://res.cloudinary.com/ape-unit/image/upload/v1617284535/nxt9o61wdvse1pdo5qya.png",
      "userflow": "gmc0zdfli",
      "tags": [
        "yfy10248i",
        "z7yu0eq11"
      ]
    },
    {
      "id": "inbk8rh27",
      "image": "https://res.cloudinary.com/ape-unit/image/upload/v1617284571/gpp9elq3odu306cmvkmo.png",
      "userflow": "gmc0zdfli",
      "tags": [
        "z7yu0eq11"
      ]
    }
  ]
}